streamlit_lottie/__init__.py
streamlit_lottie/url.py
streamlit_lottie/utils.py
streamlit_lottie/frontend/build/asset-manifest.json
streamlit_lottie/frontend/build/index.html
streamlit_lottie/frontend/build/static/css/main.e6e259fe.chunk.css
streamlit_lottie/frontend/build/static/css/main.e6e259fe.chunk.css.map
streamlit_lottie/frontend/build/static/js/2.c2e60dd1.chunk.js
streamlit_lottie/frontend/build/static/js/2.c2e60dd1.chunk.js.LICENSE.txt
streamlit_lottie/frontend/build/static/js/2.c2e60dd1.chunk.js.map
streamlit_lottie/frontend/build/static/js/main.91cf70b1.chunk.js
streamlit_lottie/frontend/build/static/js/main.91cf70b1.chunk.js.map
streamlit_lottie/frontend/build/static/js/runtime-main.9eb95e66.js
streamlit_lottie/frontend/build/static/js/runtime-main.9eb95e66.js.map
streamlit_lottie-0.0.5.dist-info/LICENSE
streamlit_lottie-0.0.5.dist-info/METADATA
streamlit_lottie-0.0.5.dist-info/WHEEL
streamlit_lottie-0.0.5.dist-info/top_level.txt
streamlit_lottie-0.0.5.dist-info/RECORD
