Metadata-Version: 2.1
Name: streamlit-lottie
Version: 0.0.5
Summary: A Streamlit custom component to load Lottie animations
Home-page: https://github.com/andfanilo/streamlit-lottie
Author: Fanilo ANDRIANASOLO
Author-email: contact@andfanilo.com
License: UNKNOWN
Platform: UNKNOWN
Requires-Python: >=3.6
